drone_flightplan/__init__.py
drone_flightplan/__version__.py
drone_flightplan/add_elevation_from_dem.py
drone_flightplan/calculate_parameters.py
drone_flightplan/call_add_elevation.py
drone_flightplan/create_flightplan.py
drone_flightplan/create_placemarks.py
drone_flightplan/drone_type.py
drone_flightplan/enums.py
drone_flightplan/flightPlanWaypointGenerator.py
drone_flightplan/sampleRasterAtPoints.py
drone_flightplan/terrain_following_waylines.py
drone_flightplan/waypoints.py
drone_flightplan/output/__init__.py
drone_flightplan/output/dji.py
drone_flightplan/output/potensic.py
drone_flightplan-0.4.1.dist-info/METADATA
drone_flightplan-0.4.1.dist-info/WHEEL
drone_flightplan-0.4.1.dist-info/licenses/LICENSE.md
drone_flightplan-0.4.1.dist-info/RECORD
