Metadata-Version: 2.4
Name: drone-flightplan
Version: 0.4.1
Summary: Generate an optimized flight plan for aerial mapping with drones.
Project-URL: homepage, https://github.com/hotosm/drone-tm/tree/develop/src/backend/packages/drone-flightplan
Project-URL: documentation, https://hotosm.github.io/drone-flightplan
Project-URL: repository, https://github.com/hotosm/drone-tm/tree/develop/src/backend/packages/drone-flightplan
Author-email: Niraj Adhikari <nrjadkry@gmail.com>
License: AGPL-3.0-only
License-File: LICENSE.md
Requires-Python: >=3.10
Requires-Dist: gdal==3.10.3
Requires-Dist: geojson>=3.0.0
Requires-Dist: pyproj>=3.7.1
Requires-Dist: shapely>=2.1.0
